{"$schema":"https://github.com/MesmerPrism/rusty-morphospace-work-environment/schemas/feature-descriptor.schema.json","schema":"rusty.morphospace.workflow.feature_descriptor.v1","feature_id":"udp-discovery","module_id":"udp-discovery","version":"0.1.0","owner_lane":"rusty-lsl","source":{"repo_id":"rusty-lsl","revision":"279b82d4551c50eb88ed23d82371edc5983103b8","path":"crates/rusty-lsl/src/udp_discovery.rs","sha256":"bc4210efbf728938f87889e1d9ea4f56ec68f1826b410c1d9e9fa5dd146e96e4"},"dependencies":[],"conflicts":[],"exclusive_group":null,"effects":{"permissions":["network access"],"services":[],"activities":[],"queries":[],"tools":[],"assets":[],"shaders":[],"native_libraries":[],"commands":[],"routes":[],"streams":[],"inputs":["explicit caller UDP discovery configuration"],"scenes":[],"markers":[]},"parameter_authorities":[{"parameter":"lsl.discovery-runtime","owner":"rusty-lsl"}],"activation":{"rule":"selected-lock-and-runtime-input","runtime_inputs":["explicit caller UDP discovery configuration"],"receipt_schema":"rusty.lsl.udp_discovery.activation_receipt.v1","effective_marker":"rusty.lsl.udp_discovery.effective"},"validation_profile":"runtime-loopback","rollback_profile":"rollback"}
